pdf_structr/README.md
pdf_structr/__init__.py
pdf_structr/extract/__init__.py
pdf_structr/extract/extract.py
pdf_structr/extract/extract_images.py
pdf_structr/extract/extract_rects.py
pdf_structr/extract/extract_tables.py
pdf_structr/extract/extract_vgs.py
pdf_structr/get_text_lines/__init__.py
pdf_structr/get_text_lines/main.py
pdf_structr/get_text_lines/make_lines_rect.py
pdf_structr/get_text_lines/make_raw_lines.py
pdf_structr/get_text_lines/make_spans_list.py
pdf_structr/get_text_lines/sanitize_spans.py
pdf_structr/header_id/__init__.py
pdf_structr/header_id/identify_hdr.py
pdf_structr/layout/__init__.py
pdf_structr/layout/compute_zone_rects.py
pdf_structr/layout/extract_blocks_compnd_bb.py
pdf_structr/layout/extract_zones.py
pdf_structr/layout/extract_zones_lib.py
pdf_structr/layout/main.py
pdf_structr/main.py
pdf_structr/main_draw.py
pdf_structr/main_utils.py
pdf_structr/multicol/__init__.py
pdf_structr/multicol/img_path_extract.py
pdf_structr/multicol/initial_block_extract.py
pdf_structr/multicol/main.py
pdf_structr/multicol/make_cols_lowlev.py
pdf_structr/multicol/make_columns.py
pdf_structr/multicol/pp_clean.py
pdf_structr/multicol/pp_join.py
pdf_structr/multicol/pp_main.py
pdf_structr/stats/__init__.py
pdf_structr/stats/augment.py
pdf_structr/stats/prep_stats.py
pdf_structr/stats/stats_block.py
pdf_structr/stats/stats_lib.py
pdf_structr/stats/stats_line.py
pdf_structr/stats/stats_page.py
pdf_structr/stats/stats_page_ftsize.py
pdf_structr/stats/stats_span.py
pdf_structr/stats/stats_x.py
pdf_structr/stats/stats_y_gaps.py
pdf_structr/tables/__init__.py
pdf_structr/tables/classes.py
pdf_structr/tables/clean_graphics.py
pdf_structr/tables/header.py
pdf_structr/tables/make_chars.py
pdf_structr/tables/make_edges.py
pdf_structr/tables/make_lines.py
pdf_structr/tables/settings.py
pdf_structr/tables/table.py
pdf_structr/tables/table_.py
pdf_structr/tables/table_funcs.py
pdf_structr/tables/tablefinder_lib.py
pdf_structr/tabls_lib/__init__.py
pdf_structr-0.1.2.dist-info/METADATA
pdf_structr-0.1.2.dist-info/WHEEL
pdf_structr-0.1.2.dist-info/RECORD
