Metadata-Version: 2.1
Name: pdf-structr
Version: 0.1.2
Summary: Tool to extract the structure of a PDF
License: Proprietary
Author: Cedric Lor
Author-email: cedric.lor@gmail.com
Requires-Python: >=3.11,<4.0
Classifier: License :: Other/Proprietary License
Classifier: Programming Language :: Python :: 3
Classifier: Programming Language :: Python :: 3.11
Classifier: Programming Language :: Python :: 3.12
Classifier: Programming Language :: Python :: 3.13
Requires-Dist: numpy (>=1,<2)
Requires-Dist: pymupdf (>=1.24.13,<2.0.0)
